setup.py
dataprocess/__init__.py
dataprocess/describe.py
dataprocess/null_replace_method.py
dataprocess/widgets.py
jupyter_dataprocess.egg-info/PKG-INFO
jupyter_dataprocess.egg-info/SOURCES.txt
jupyter_dataprocess.egg-info/dependency_links.txt
jupyter_dataprocess.egg-info/requires.txt
jupyter_dataprocess.egg-info/top_level.txt