Metadata-Version: 1.0
Name: jupyter-dataprocess
Version: 0.0.1
Summary: Jupyter Widgets for data cleaning and preprocessing
Home-page: https://github.com/saili109/jupyter-dataprocess
Author: Sai Li
Author-email: sailiinuk@gmail.com
License: MIT
Platform: UNKNOWN
